chatting_live/__init__.py
chatting_live/client.py
chatting_live-0.1.14.dist-info/licenses/LICENSE
chatting_live-0.1.14.dist-info/METADATA
chatting_live-0.1.14.dist-info/WHEEL
chatting_live-0.1.14.dist-info/entry_points.txt
chatting_live-0.1.14.dist-info/top_level.txt
chatting_live-0.1.14.dist-info/RECORD
